cas/__init__.py
cas/cli.py
cas/common/__init__.py
cas/common/cache.py
cas/common/config.py
cas/common/models.py
cas/common/sequencer.py
cas/common/steamtools.py
cas/common/utilities.py
cas/common/assets/__init__.py
cas/common/assets/models.py
cas/common/assets/drivers/__init__.py
cas/common/assets/drivers/caption.py
cas/common/assets/drivers/model.py
cas/common/assets/drivers/vice.py
cas/common/buildsys/__init__.py
cas/common/buildsys/msbuild.py
cas/common/buildsys/posix.py
cas/common/buildsys/shared.py
cas/common/buildsys/vpc.py
cas/schemas/root.json
cas/schemas/drivers/caption.json
cas/schemas/drivers/model.json
cas/schemas/drivers/vice.json
cas/schemas/subsystems/assets.json
cas/schemas/subsystems/buildsys.json
cas/schemas/subsystems/custom.json
cas/schemas/subsystems/fgdbuild.json
cas/schemas/subsystems/panzip.json
cas/schemas/subsystems/steamworks.json
cas/schemas/subsystems/syncfolder.json
cas/schemas/subsystems/vpk.json
cas/subsystems/__init__.py
cas/subsystems/assets.py
cas/subsystems/buildsys.py
cas/subsystems/custom.py
cas/subsystems/fgdbuild.py
cas/subsystems/panzip.py
cas/subsystems/steamworks.py
cas/subsystems/syncfolder.py
cas/subsystems/vpk.py
cas-1.0.10.dist-info/LICENSE
cas-1.0.10.dist-info/METADATA
cas-1.0.10.dist-info/WHEEL
cas-1.0.10.dist-info/dependency_links.txt
cas-1.0.10.dist-info/entry_points.txt
cas-1.0.10.dist-info/top_level.txt
cas-1.0.10.dist-info/RECORD
