Metadata-Version: 2.1
Name: cas
Version: 1.0.10
Summary: Chaos Automation System
Home-page: https://github.com/ChaosInitiative/CAS
Author: Chaos Initiative
Author-email: contact@chaosinitiative.com
License: mit
Platform: UNKNOWN
Classifier: Programming Language :: Python :: 3
Classifier: License :: OSI Approved :: MIT License
Classifier: Operating System :: OS Independent
Requires-Python: >=3.7
Requires-Dist: jsonschema
Requires-Dist: simpleeval
Requires-Dist: appdirs
Requires-Dist: dotmap
Requires-Dist: tqdm
Requires-Dist: vdf
Requires-Dist: requests
